worksheetgen/__init__.py
worksheetgen/wg.py
worksheetgen-0.1.0.dist-info/METADATA
worksheetgen-0.1.0.dist-info/WHEEL
worksheetgen-0.1.0.dist-info/top_level.txt
worksheetgen-0.1.0.dist-info/RECORD
