Metadata-Version: 2.1
Name: worksheetgen
Version: 0.1.0
Summary: A worksheet generator
Home-page: https://github.com/lukew3/worksheetgen
Author: Luke Weiler
Author-email: lukew25073@gmail.com
License: MIT
Platform: UNKNOWN
Requires-Dist: weasyprint
Requires-Dist: requests-file
Requires-Dist: requests-html
Requires-Dist: domonic
